fitz_utils/__init__.py
fitz_utils/processed_doc.py
fitz_utils/processed_page.py
fitz_utils-1.0.4.dist-info/LICENSE
fitz_utils-1.0.4.dist-info/METADATA
fitz_utils-1.0.4.dist-info/WHEEL
fitz_utils-1.0.4.dist-info/RECORD
