Metadata-Version: 2.1
Name: fitz-utils
Version: 1.0.4
Summary: Extra functions for use with pymupdf module
Author: The Walnut AI
Requires-Python: >=3.10,<4.0
Classifier: Programming Language :: Python :: 3
Classifier: Programming Language :: Python :: 3.10
Classifier: Programming Language :: Python :: 3.11
Classifier: Programming Language :: Python :: 3.12
Requires-Dist: ftfy (>=6.1.1,<7.0.0)
Requires-Dist: numpy (>=1.26.1,<2.0.0)
Requires-Dist: pandas (>=2.1.1,<3.0.0)
Requires-Dist: pymupdf (>=1.20.0,<2.0.0)
